bounty_dork/__init__.py
bounty_dork/bounty_dork.py
bounty_dork/dorks/__init__.py
bounty_dork/dorks/github_dorking.py
bounty_dork/dorks/search_engine_dorking.py
bounty_dork/dorks/shodan_dorking.py
bounty_dork/reporting/__init__.py
bounty_dork/reporting/results_manager.py
bounty_dork/requester/__init__.py
bounty_dork/requester/request_manager.py
bounty_dork/requester/request_parser.py
bounty_dork/scraping/__init__.py
bounty_dork/scraping/web_scraper.py
bounty_dork/utils/__init__.py
bounty_dork/utils/app_config.py
bounty_dork/utils/banner.py
bounty_dork/utils/logger.py
bounty_dork/vpn_proxies/__init__ copy.py
bounty_dork/vpn_proxies/__init__.py
bounty_dork/vpn_proxies/proxies_manager.py
bounty_dork/vpn_proxies/vpn_manager.py
bounty_dork/vpn_proxies/nordvpn_switcher/__init__.py
bounty_dork/vpn_proxies/nordvpn_switcher/demo.py
bounty_dork/vpn_proxies/nordvpn_switcher/nordvpn_switch.py
bounty_dork-0.0.1.dist-info/METADATA
bounty_dork-0.0.1.dist-info/WHEEL
bounty_dork-0.0.1.dist-info/top_level.txt
bounty_dork-0.0.1.dist-info/RECORD
