Metadata-Version: 2.1
Name: bounty-dork
Version: 0.0.1
Summary: Automated Google Dorking tool for pentesters without API keys.
Home-page: https://github.com/ElNiak/BountyDork
Author: ElNiak
Author-email: christophe.crochet@uclouvain.be
Maintainer: ElNiak
Maintainer-email: christophe.crochet@uclouvain.be
Classifier: Intended Audience :: Developers
Classifier: Programming Language :: Python :: 3.6
Classifier: Topic :: Software Development :: Libraries :: Python Modules
